EUPL-LICENSE.md
README.md
setup.cfg
setup.py
docker_systemctl_replacement.egg-info/PKG-INFO
docker_systemctl_replacement.egg-info/SOURCES.txt
docker_systemctl_replacement.egg-info/dependency_links.txt
docker_systemctl_replacement.egg-info/top_level.txt
src/README.md
src/systemctl.py
src/systemctl.pyi