Metadata-Version: 2.1
Name: docker-systemctl-replacement
Version: 1.5.8066
Summary: allows to deploy to systemd-controlled containers without starting an actual systemd daemon
Home-page: https://github.com/gdraheim/docker-systemctl-replacement
Author: Guido U. Draheim
Author-email: Guido.Draheim@gmx.de
License: EUPL
Platform: UNKNOWN
